keras_facenet/__init__.py
keras_facenet/embedding_model.py
keras_facenet/inception_resnet_v1.py
keras_facenet/metadata.py
keras_facenet/utils.py
keras_facenet-0.3.1.dist-info/LICENSE
keras_facenet-0.3.1.dist-info/METADATA
keras_facenet-0.3.1.dist-info/WHEEL
keras_facenet-0.3.1.dist-info/top_level.txt
keras_facenet-0.3.1.dist-info/RECORD
